textual_englyph/__init__.py
textual_englyph/_englyph_image.py
textual_englyph/_englyph_seven_segment.py
textual_englyph/_englyph_text.py
textual_englyph/englyph.py
textual_englyph/main_demo.py
textual_englyph/py.typed
textual_englyph/toglyxels.py
textual_englyph/assets/AtariSmall.ttf
textual_englyph/assets/EnSevSeg_8x5.ttf
textual_englyph/assets/NotoColorEmoji.ttf
textual_englyph/assets/TerminusTTF-4.46.0.ttf
textual_englyph/assets/Zepto-Regular.ttf
textual_englyph/assets/casio-fx-9860gii.ttf
textual_englyph/assets/hgjb.ttf
textual_englyph/assets/miniwi.ttf
textual_englyph/assets/seven_seg_bm.ttf
textual_englyph-0.5.4.dist-info/METADATA
textual_englyph-0.5.4.dist-info/WHEEL
textual_englyph-0.5.4.dist-info/entry_points.txt
textual_englyph-0.5.4.dist-info/RECORD
