Metadata-Version: 2.4
Name: textual-englyph
Version: 0.5.4
Summary: A Textual utility widget set to generate terminal images and styled, scalable text.
License: MIT License
Requires-Python: >=3.9
Requires-Dist: pillow>=10.4.0
Requires-Dist: textual>=2.1.2
